kang_eda-0.4.2.dist-info/METADATA
kang_eda-0.4.2.dist-info/WHEEL
kang_eda-0.4.2.dist-info/entry_points.txt
kang_eda/__init__.py
kang_eda/cli.py
kang_eda-0.4.2.dist-info/RECORD
