Metadata-Version: 2.1
Name: kang-eda
Version: 0.4.2
Summary: Default template for PDM package
Author-Email: khr0106 <kanghr990106@gmail.com>
License: MIT
Requires-Python: >=3.10
Requires-Dist: pandas>=2.2.3
Requires-Dist: president-speech>=0.9.1
Requires-Dist: typer>=0.15.1
